[{"open_date":"8-2-2021 @ 6:0","close_date":"8-2-2021 @ 6:59","close_price":0.0779247,"close_date_ut":1612742399999},{"open_date":"8-2-2021 @ 7:0","close_date":"8-2-2021 @ 7:59","close_price":0.069526,"close_date_ut":1612745999999},{"open_date":"8-2-2021 @ 8:0","close_date":"8-2-2021 @ 8:59","close_price":0.0763066,"close_date_ut":1612749599999},{"open_date":"8-2-2021 @ 9:0","close_date":"8-2-2021 @ 9:59","close_price":0.0715046,"close_date_ut":1612753199999},{"open_date":"8-2-2021 @ 10:0","close_date":"8-2-2021 @ 10:59","close_price":0.0660992,"close_date_ut":1612756799999},{"open_date":"8-2-2021 @ 11:0","close_date":"8-2-2021 @ 11:59","close_price":0.0710344,"close_date_ut":1612760399999},{"open_date":"8-2-2021 @ 12:0","close_date":"8-2-2021 @ 12:59","close_price":0.0708246,"close_date_ut":1612763999999},{"open_date":"8-2-2021 @ 13:0","close_date":"8-2-2021 @ 13:59","close_price":0.071364,"close_date_ut":1612767599999},{"open_date":"8-2-2021 @ 14:0","close_date":"8-2-2021 @ 14:59","close_price":0.0718143,"close_date_ut":1612771199999},{"open_date":"8-2-2021 @ 15:0","close_date":"8-2-2021 @ 15:59","close_price":0.0712857,"close_date_ut":1612774799999}]2772099999}]